pywikibot/__init__.py
pywikibot/__metadata__.py
pywikibot/_wbtypes.py
pywikibot/backports.py
pywikibot/bot.py
pywikibot/bot_choice.py
pywikibot/config.py
pywikibot/cosmetic_changes.py
pywikibot/daemonize.py
pywikibot/date.py
pywikibot/diff.py
pywikibot/echo.py
pywikibot/editor.py
pywikibot/exceptions.py
pywikibot/family.py
pywikibot/fixes.py
pywikibot/i18n.py
pywikibot/interwiki_graph.py
pywikibot/logentries.py
pywikibot/logging.py
pywikibot/login.py
pywikibot/plural.py
pywikibot/proofreadpage.py
pywikibot/site_detect.py
pywikibot/textlib.py
pywikibot/throttle.py
pywikibot/time.py
pywikibot/titletranslate.py
pywikibot/version.py
pywikibot/xmlreader.py
pywikibot/comms/__init__.py
pywikibot/comms/eventstreams.py
pywikibot/comms/http.py
pywikibot/data/__init__.py
pywikibot/data/citoid.py
pywikibot/data/memento.py
pywikibot/data/mysql.py
pywikibot/data/sparql.py
pywikibot/data/superset.py
pywikibot/data/wikistats.py
pywikibot/data/api/__init__.py
pywikibot/data/api/_generators.py
pywikibot/data/api/_optionset.py
pywikibot/data/api/_paraminfo.py
pywikibot/data/api/_requests.py
pywikibot/families/__init__.py
pywikibot/families/commons_family.py
pywikibot/families/foundation_family.py
pywikibot/families/i18n_family.py
pywikibot/families/incubator_family.py
pywikibot/families/lingualibre_family.py
pywikibot/families/mediawiki_family.py
pywikibot/families/meta_family.py
pywikibot/families/osm_family.py
pywikibot/families/outreach_family.py
pywikibot/families/species_family.py
pywikibot/families/vikidia_family.py
pywikibot/families/wikibooks_family.py
pywikibot/families/wikidata_family.py
pywikibot/families/wikifunctions_family.py
pywikibot/families/wikihow_family.py
pywikibot/families/wikimania_family.py
pywikibot/families/wikimediachapter_family.py
pywikibot/families/wikinews_family.py
pywikibot/families/wikipedia_family.py
pywikibot/families/wikiquote_family.py
pywikibot/families/wikisource_family.py
pywikibot/families/wikispore_family.py
pywikibot-10.7.6.dist-info/licenses/AUTHORS.rst
pywikibot-10.7.6.dist-info/licenses/LICENSE
pywikibot-10.7.6.dist-info/METADATA
pywikibot-10.7.6.dist-info/WHEEL
pywikibot-10.7.6.dist-info/entry_points.txt
pywikibot-10.7.6.dist-info/top_level.txt
pywikibot-10.7.6.dist-info/RECORD
