Metadata-Version: 2.4
Name: pywikibot
Version: 10.7.6
Summary: Python MediaWiki Bot Framework
Author-email: xqt <info@gno.de>
Maintainer-email: The Pywikibot team <pywikibot@lists.wikimedia.org>
License: MIT License
Project-URL: Homepage, https://www.mediawiki.org/wiki/Manual:Pywikibot
Project-URL: Documentation, https://doc.wikimedia.org/pywikibot/stable/
Project-URL: Repository, https://gerrit.wikimedia.org/r/plugins/gitiles/pywikibot/core/
Project-URL: GitHub Mirror, https://github.com/wikimedia/pywikibot
Project-URL: Download, https://www.pywikibot.org
Project-URL: Changelog, https://doc.wikimedia.org/pywikibot/master/changelog.html
Project-URL: Tracker, https://phabricator.wikimedia.org/tag/pywikibot/
Keywords: API,bot,client,framework,mediawiki,pwb,pybot,python,pywiki,pywikibase,pywikibot,pywikipedia,pywikipediabot,wiki,wikibase,wikidata,wikimedia,wikipedia
Classifier: Development Status :: 5 - Production/Stable
Classifier: Environment :: Console
Classifier: Intended Audience :: Developers
Classifier: License :: OSI Approved :: MIT License
Classifier: Natural Language :: Afrikaans
Classifier: Natural Language :: Arabic
Classifier: Natural Language :: Basque
Classifier: Natural Language :: Bengali
Classifier: Natural Language :: Bosnian
Classifier: Natural Language :: Bulgarian
Classifier: Natural Language :: Cantonese
Classifier: Natural Language :: Catalan
Classifier: Natural Language :: Chinese (Simplified)
Classifier: Natural Language :: Chinese (Traditional)
Classifier: Natural Language :: Croatian
Classifier: Natural Language :: Czech
Classifier: Natural Language :: Danish
Classifier: Natural Language :: Dutch
Classifier: Natural Language :: English
Classifier: Natural Language :: Esperanto
Classifier: Natural Language :: Finnish
Classifier: Natural Language :: French
Classifier: Natural Language :: Galician
Classifier: Natural Language :: German
Classifier: Natural Language :: Greek
Classifier: Natural Language :: Hebrew
Classifier: Natural Language :: Hindi
Classifier: Natural Language :: Hungarian
Classifier: Natural Language :: Icelandic
Classifier: Natural Language :: Indonesian
Classifier: Natural Language :: Irish
Classifier: Natural Language :: Italian
Classifier: Natural Language :: Japanese
Classifier: Natural Language :: Javanese
Classifier: Natural Language :: Korean
Classifier: Natural Language :: Latin
Classifier: Natural Language :: Latvian
Classifier: Natural Language :: Lithuanian
Classifier: Natural Language :: Macedonian
Classifier: Natural Language :: Malay
Classifier: Natural Language :: Marathi
Classifier: Natural Language :: Nepali
Classifier: Natural Language :: Norwegian
Classifier: Natural Language :: Panjabi
Classifier: Natural Language :: Persian
Classifier: Natural Language :: Polish
Classifier: Natural Language :: Portuguese
Classifier: Natural Language :: Portuguese (Brazilian)
Classifier: Natural Language :: Romanian
Classifier: Natural Language :: Russian
Classifier: Natural Language :: Serbian
Classifier: Natural Language :: Slovak
Classifier: Natural Language :: Slovenian
Classifier: Natural Language :: Spanish
Classifier: Natural Language :: Swedish
Classifier: Natural Language :: Tamil
Classifier: Natural Language :: Telugu
Classifier: Natural Language :: Thai
Classifier: Natural Language :: Tibetan
Classifier: Natural Language :: Turkish
Classifier: Natural Language :: Ukrainian
Classifier: Natural Language :: Urdu
Classifier: Natural Language :: Vietnamese
Classifier: Operating System :: OS Independent
Classifier: Programming Language :: Python
Classifier: Programming Language :: Python :: 3
Classifier: Programming Language :: Python :: 3 :: Only
Classifier: Programming Language :: Python :: 3.8
Classifier: Programming Language :: Python :: 3.9
Classifier: Programming Language :: Python :: 3.10
Classifier: Programming Language :: Python :: 3.11
Classifier: Programming Language :: Python :: 3.12
Classifier: Programming Language :: Python :: 3.13
Classifier: Programming Language :: Python :: 3.14
Classifier: Programming Language :: Python :: 3.15
Classifier: Programming Language :: Python :: Implementation :: CPython
Classifier: Programming Language :: Python :: Implementation :: PyPy
Classifier: Topic :: Internet :: WWW/HTTP :: Dynamic Content :: Wiki
Classifier: Topic :: Software Development :: Libraries :: Python Modules
Classifier: Topic :: Utilities
Requires-Python: >=3.8.0
License-File: LICENSE
License-File: AUTHORS.rst
Requires-Dist: mwparserfromhell>=0.5.2
Requires-Dist: packaging
Requires-Dist: requests>=2.31.0
Provides-Extra: eventstreams
Requires-Dist: requests-sse>=0.5.0; extra == "eventstreams"
Provides-Extra: isbn
Requires-Dist: python-stdnum>=1.20; extra == "isbn"
Provides-Extra: graphviz
Requires-Dist: pydot>=3.0.2; extra == "graphviz"
Provides-Extra: google
Requires-Dist: googlesearch-python>=1.3.0; extra == "google"
Provides-Extra: memento
Requires-Dist: memento_client==0.6.1; extra == "memento"
Provides-Extra: wikitextparser
Requires-Dist: wikitextparser>=0.56.3; extra == "wikitextparser"
Provides-Extra: mysql
Requires-Dist: PyMySQL>=1.1.1; extra == "mysql"
Provides-Extra: tkinter
Requires-Dist: Pillow==10.4.0; (platform_python_implementation == "PyPy" and python_version < "3.9") and extra == "tkinter"
Requires-Dist: Pillow<11.3.0,>=11.1.0; (platform_python_implementation == "PyPy" and python_version >= "3.9" and python_version < "3.11") and extra == "tkinter"
Requires-Dist: Pillow>=11.1.0; (platform_python_implementation == "PyPy" and python_version >= "3.11") and extra == "tkinter"
Requires-Dist: Pillow==10.4.0; (platform_python_implementation != "PyPy" and python_version < "3.9") and extra == "tkinter"
Requires-Dist: Pillow<11.3.0,>=11.1.0; (platform_python_implementation != "PyPy" and python_version == "3.9") and extra == "tkinter"
Requires-Dist: Pillow>=11.1.0; (platform_python_implementation != "PyPy" and python_version >= "3.10") and extra == "tkinter"
Provides-Extra: mwoauth
Requires-Dist: PyJWT!=2.10.0,!=2.10.1; python_version > "3.8" and extra == "mwoauth"
Requires-Dist: mwoauth!=0.3.1,>=0.2.4; extra == "mwoauth"
Provides-Extra: html
Requires-Dist: beautifulsoup4>=4.7.1; extra == "html"
Provides-Extra: http
Requires-Dist: fake-useragent>=2.0.3; python_version > "3.8" and extra == "http"
Requires-Dist: fake-useragent==1.5.1; python_version < "3.9" and extra == "http"
Provides-Extra: create-isbn-edition-py
Requires-Dist: isbnlib; extra == "create-isbn-edition-py"
Requires-Dist: unidecode; extra == "create-isbn-edition-py"
Provides-Extra: weblinkchecker-py
Requires-Dist: memento_client==0.6.1; extra == "weblinkchecker-py"
Provides-Extra: scripts
Requires-Dist: isbnlib; extra == "scripts"
Requires-Dist: unidecode; extra == "scripts"
Requires-Dist: memento_client==0.6.1; extra == "scripts"
Dynamic: description
Dynamic: description-content-type
Dynamic: license-file
Dynamic: provides-extra
Dynamic: requires-dist
